{
  "id": "02bdbec85b21",
  "slug": "i-loved--02bdbec85b21",
  "title": "I Loved . . .",
  "content": "    I loved illustrious cities and the crowds\r\n    That eddy through their incandescent nights.\r\n    I loved remote horizons with far clouds\r\n    Girdled, and fringed about with snowy heights.\r\n    I loved fair women, their sweet, conscious ways\r\n    Of wearing among hands that covet and plead\r\n    The rose ablossom at the rainbow's base\r\n    That bounds the world's desire and all its need.\r\n    Nature I worshipped, whose fecundity\r\n    Embraces every vision the most fair,\r\n    Of perfect benediction. From a boy\r\n    I gloated on existence. Earth to me\r\n    Seemed all-sufficient and my sojourn there\r\n    One trembling opportunity for joy.",
  "writer": "Alan Seeger",
  "category": [
    "classic"
  ],
  "meaning": "This evocative piece by Alan Seeger represents a masterful exploration of classic. The lines capture a profound emotional resonance, inviting the reader to reflect on the deeper themes of human experience and artistic expression.\n\nIn the broader context of Alan Seeger's bibliography, these specific lines stand out for their clarity and poignancy. Whether you are searching for inspiration or a moment of quiet contemplation, this work offers a timeless perspective that transcends its original era.\n\nAt Linespedia, we have curated this specific poem to ensure it reaches a modern audience. We recommend sharing these lines as a digital poster or using them as a thoughtful caption to connect with others who appreciate the enduring beauty of verse.",
  "meta": {
    "views": 1565,
    "dates": "June 22, 1888 - July 4, 1916"
  }
}