{
  "id": "07d8d8fdaac8",
  "slug": "amadis-and-oriana-07d8d8fdaac8",
  "title": "Amadis And Oriana",
  "content": "From \"Beltenebros at Miraflores\"\n\r\n    O sunset, from the springs of stars\r\n    Draw down thy cataracts of gold;\r\n    And belt their streams with burning bars\r\n    Of ruby on which flame is rolled:\r\n    Drench dingles with laburnum light;\r\n    Drown every vale in violet blaze:\r\n    Rain rose-light down; and, poppy-bright,\r\n    Die downward o'er the hills of haze,\r\n    And bring at last the stars of night!\n\r\n    The stars and moon! that silver world,\r\n    Which, like a spirit, faces west,\r\n    Her foam-white feet with light empearled,\r\n    Bearing white flame within her breast:\r\n    Earth's sister sphere of fire and snow,\r\n    Who shows to Earth her heart's pale heat,\r\n    And bids her mark its pulses glow,\r\n    And hear their crystal currents beat\r\n    With beauty, lighting all below.\n\r\n    O cricket, with thy elfin pipe,\r\n    That tinkles in the grass and grain;\r\n    And dove-pale buds, that, dropping, stripe\r\n    The glen's blue night, and smell of rain;\r\n    O nightingale, that so dost wail\r\n    On yonder blossoming branch of snow,\r\n    Thrill, fill the wild deer-haunted dale,\r\n    Where Oriana, walking slow,\r\n    Comes, thro' the moonlight, dreamy pale.\n\r\n    She comes to meet me! - Earth and air\r\n    Grow radiant with another light.\r\n    In her dark eyes and her dark hair\r\n    Are all the stars and all the night:\r\n    She comes! I clasp her! - and it is\r\n    As if no grief had ever been. - \r\n    In all the world for us who kiss\r\n    There are no other women or men\r\n    But Oriana and Amadis.",
  "writer": "Madison Julius Cawein",
  "category": [
    "classic"
  ],
  "meaning": "This evocative piece by Madison Julius Cawein represents a masterful exploration of classic. The lines capture a profound emotional resonance, inviting the reader to reflect on the deeper themes of human experience and artistic expression.\n\nIn the broader context of Madison Julius Cawein's bibliography, these specific lines stand out for their clarity and poignancy. Whether you are searching for inspiration or a moment of quiet contemplation, this work offers a timeless perspective that transcends its original era.\n\nAt Linespedia, we have curated this specific poem to ensure it reaches a modern audience. We recommend sharing these lines as a digital poster or using them as a thoughtful caption to connect with others who appreciate the enduring beauty of verse.",
  "meta": {
    "views": 1607,
    "dates": "23 March 1865 - 8 December 1914"
  }
}