{
  "id": "09e1b857d5a6",
  "slug": "the-albatross-09e1b857d5a6",
  "title": "The Albatross",
  "content": "    Often, to amuse themselves, the crew of the ship\r\n    Would fell an albatross, the largest of sea birds,\r\n    Indolent companions of their trip\r\n    As they slide across the deep sea's bitters.\n\r\n    Scarcely had they dropped to the plank\r\n    Than these blue kings, maladroit and ashamed\r\n    Let their great white wings sink\r\n    Like an oar dragging under the water's plane.\n\r\n    The winged visitor, so awkward and weak!\r\n    So recently beautiful, now comic and ugly!\r\n    One sailor grinds a pipe into his beak,\r\n    Another, limping, mimics the infirm bird that once could fly.\n\r\n    The poet is like the prince of the clouds\r\n    Who haunts the storm and laughs at lightning.\r\n    He's exiled to the ground and its hooting crowds;\r\n    His giant wings prevent him from walking.\n",
  "writer": "Charles Baudelaire",
  "category": [
    "classic"
  ],
  "meaning": "This evocative piece by Charles Baudelaire represents a masterful exploration of classic. The lines capture a profound emotional resonance, inviting the reader to reflect on the deeper themes of human experience and artistic expression.\n\nIn the broader context of Charles Baudelaire's bibliography, these specific lines stand out for their clarity and poignancy. Whether you are searching for inspiration or a moment of quiet contemplation, this work offers a timeless perspective that transcends its original era.\n\nAt Linespedia, we have curated this specific poem to ensure it reaches a modern audience. We recommend sharing these lines as a digital poster or using them as a thoughtful caption to connect with others who appreciate the enduring beauty of verse.",
  "meta": {
    "views": 2011,
    "dates": "April 9, 1821 - August 31, 1867"
  }
}