{
  "id": "0a2ea9c26a02",
  "slug": "misty-sky-0a2ea9c26a02",
  "title": "Misty Sky",
  "content": "    A vapour seems to hide your face from view;\r\n    Your mystic eye (is it green, grey, or blue?)\r\n    Tender by turns, dreamy or merciless,\r\n    Reflects the heavens' pallid indolence.\n\r\n    You call to mind white, mild, enshrouded days\r\n    That make enchanted hearts dissolve away,\r\n    When, agitated by a twisting ache,\r\n    The taut nerves call the spirit to awake.\n\r\n    Sometimes you're like horizons set aglow\r\n    By suns in rainy seasons here below...\r\n    Like you superb, a watery countryside\r\n    That rays enflame out of a misty sky!\n\r\n    O weather! woman! - both seduce me so!\r\n    Will I adore as well your frost and snow,\r\n    And will I draw from winter's ruthless vice\r\n    Pleasures more keen than iron or than ice?",
  "writer": "Charles Baudelaire",
  "category": [
    "classic"
  ],
  "meaning": "This evocative piece by Charles Baudelaire represents a masterful exploration of classic. The lines capture a profound emotional resonance, inviting the reader to reflect on the deeper themes of human experience and artistic expression.\n\nIn the broader context of Charles Baudelaire's bibliography, these specific lines stand out for their clarity and poignancy. Whether you are searching for inspiration or a moment of quiet contemplation, this work offers a timeless perspective that transcends its original era.\n\nAt Linespedia, we have curated this specific poem to ensure it reaches a modern audience. We recommend sharing these lines as a digital poster or using them as a thoughtful caption to connect with others who appreciate the enduring beauty of verse.",
  "meta": {
    "views": 2004,
    "dates": "April 9, 1821 - August 31, 1867"
  }
}