{
  "id": "169163ca4c8a",
  "slug": "don-diego-of-the-south-169163ca4c8a",
  "title": "Don Diego of the South",
  "content": "ֲ ֲ ֲ ֲ Good! said the Padre, believe me still,\r\nֲ ֲ ֲ ֲ ן¿½Don Giovanni,ן¿½ or what you will,\r\nֲ ֲ ֲ ֲ The typeן¿½s eternal! We knew him here\r\nֲ ֲ ֲ ֲ As Don Diego del Sud. I fear\r\nֲ ֲ ֲ ֲ The storyן¿½s no new one! Will you hear?\n\r\nֲ ֲ ֲ ֲ One of those spirits you canן¿½t tell why\r\nֲ ֲ ֲ ֲ God has permitted. Therein I\r\nֲ ֲ ֲ ֲ Have the advantage, for I hold\r\nֲ ֲ ֲ ֲ That wolves are sent to the purest fold,\r\nֲ ֲ ֲ ֲ And weן¿½d save the wolf if weן¿½d get the lamb.\r\nֲ ֲ ֲ ֲ Youן¿½re no believer? Good! I am.\n\r\nֲ ֲ ֲ ֲ Well, for some purpose, I grant you dim,\r\nֲ ֲ ֲ ֲ The Don loved women, and they loved him.\r\nֲ ֲ ֲ ֲ Each thought herself his last love! Worst,\r\nֲ ֲ ֲ ֲ Many believed that they were his first!\r\nֲ ֲ ֲ ֲ And, such are these creatures since the Fall,\r\nֲ ֲ ֲ ֲ The very doubt had a charm for all!\n\r\nֲ ֲ ֲ ֲ You laugh! You are young, but I indeed\r\nֲ ֲ ֲ ֲ I have no patience . . . To proceed:\r\nֲ ֲ ֲ ֲ You saw, as you passed through the upper town,\r\nֲ ֲ ֲ ֲ The Eucinal where the road goes down\r\nֲ ֲ ֲ ֲ To San Felipe! There one morn\r\nֲ ֲ ֲ ֲ They found Diego, his mantle torn,\r\nֲ ֲ ֲ ֲ And as many holes through his doubletן¿½s band\r\nֲ ֲ ֲ ֲ As there were wronged husbands you understand!\n\r\nֲ ֲ ֲ ֲ ן¿½Dying,ן¿½ so said the gossips. ן¿½Deadן¿½\r\nֲ ֲ ֲ ֲ Was what the friars who found him said.\r\nֲ ֲ ֲ ֲ May be. Quien sabe? Who else should know?\r\nֲ ֲ ֲ ֲ It was a hundred years ago.\r\nֲ ֲ ֲ ֲ There was a funeral. Small indeed\r\nֲ ֲ ֲ ֲ Private. What would you? To proceed:\n\r\nֲ ֲ ֲ ֲ Scarcely the year had flown. One night\r\nֲ ֲ ֲ ֲ The Commandante awoke in fright,\r\nֲ ֲ ֲ ֲ Hearing below his casementן¿½s bar\r\nֲ ֲ ֲ ֲ The well-known twang of the Donן¿½s guitar;\r\nֲ ֲ ֲ ֲ And rushed to the window, just to see\r\nֲ ֲ ֲ ֲ His wife a-swoon on the balcony.\n\r\nֲ ֲ ֲ ֲ One week later, Don Juan Ramirez\r\nֲ ֲ ֲ ֲ Found his own daughter, the Dona Inez,\r\nֲ ֲ ֲ ֲ Pale as a ghost, leaning out to hear\r\nֲ ֲ ֲ ֲ The song of that phantom cavalier.\r\nֲ ֲ ֲ ֲ Even Alcalde Pedro Blas\r\nֲ ֲ ֲ ֲ Saw, it was said, through his nieceן¿½s glass,\r\nֲ ֲ ֲ ֲ The shade of Diego twice repass.\n\r\nֲ ֲ ֲ ֲ What these gentlemen each confessed\r\nֲ ֲ ֲ ֲ Heaven and the Church only knows. At best\r\nֲ ֲ ֲ ֲ The case was a bad one. How to deal\r\nֲ ֲ ֲ ֲ With Sin as a Ghost, they couldnן¿½t but feel\r\nֲ ֲ ֲ ֲ Was an awful thing. Till a certain Fray\r\nֲ ֲ ֲ ֲ Humbly offered to show the way.\n\r\nֲ ֲ ֲ ֲ And the way was this. Did I say before\r\nֲ ֲ ֲ ֲ That the Fray was a stranger? No, Seן¿½or?\r\nֲ ֲ ֲ ֲ Strange! very strange! I should have said\r\nֲ ֲ ֲ ֲ That the very week that the Don lay dead\r\nֲ ֲ ֲ ֲ He came among us. Bread he broke\r\nֲ ֲ ֲ ֲ Silent, nor ever to one he spoke.\r\nֲ ֲ ֲ ֲ So he had vowed it! Below his brows\r\nֲ ֲ ֲ ֲ His face was hidden. There are such vows!\n\r\nֲ ֲ ֲ ֲ Strange! are they not? You do not use\r\nֲ ֲ ֲ ֲ Snuff? A bad habit!\n\r\nֲ ֲ ֲ ֲ  Well, the views\r\nֲ ֲ ֲ ֲ Of the Fray were these: that the penance done\r\nֲ ֲ ֲ ֲ By the caballeros was right; but one\r\nֲ ֲ ֲ ֲ Was due from the cause, and that, in brief,\r\nֲ ֲ ֲ ֲ Was Dona Dolores Gomez, chief,\r\nֲ ֲ ֲ ֲ And Inez, Sanchicha, Concepcion,\r\nֲ ֲ ֲ ֲ And Carmen, well, half the girls in town\r\nֲ ֲ ֲ ֲ On his tablets the Friar had written down.\n\r\nֲ ֲ ֲ ֲ These were to come on a certain day\r\nֲ ֲ ֲ ֲ And ask at the hands of the pious Fray\r\nֲ ֲ ֲ ֲ For absolution. That done, small fear\r\nֲ ֲ ֲ ֲ But the shade of Diego would disappear.\n\r\nֲ ֲ ֲ ֲ They came; each knelt in her turn and place\r\nֲ ֲ ֲ ֲ To the pious Fray with his hidden face\r\nֲ ֲ ֲ ֲ And voiceless lips, and each again\r\nֲ ֲ ֲ ֲ Took back her soul freed from spot or stain,\r\nֲ ֲ ֲ ֲ Till the Dona Inez, with eyes downcast\r\nֲ ֲ ֲ ֲ And a tear on their fringes, knelt her last.\n\r\nֲ ֲ ֲ ֲ And then perhaps that her voice was low\r\nֲ ֲ ֲ ֲ From fear or from shame the monks said so\r\nֲ ֲ ֲ ֲ But the Fray leaned forward, when, presto! all\r\nֲ ֲ ֲ ֲ Were thrilled by a scream, and saw her fall\r\nֲ ֲ ֲ ֲ Fainting beside the confessional.\n\r\nֲ ֲ ֲ ֲ And so was the ghost of Diego laid\r\nֲ ֲ ֲ ֲ As the Fray had said. Never more his shade\r\nֲ ֲ ֲ ֲ Was seen at San Gabrielן¿½s Mission. Eh!\r\nֲ ֲ ֲ ֲ The girl interests you? I dare say!\r\nֲ ֲ ֲ ֲ ן¿½Nothing,ן¿½ said she, when they brought her to\r\nֲ ֲ ֲ ֲ ן¿½Only a faintness!ן¿½ They spoke more true\r\nֲ ֲ ֲ ֲ Who said ן¿½twas a stubborn soul. But then\r\nֲ ֲ ֲ ֲ Women are women, and men are men!\n\r\nֲ ֲ ֲ ֲ So, to return. As I said before,\r\nֲ ֲ ֲ ֲ Having got the wolf, by the same high law\r\nֲ ֲ ֲ ֲ We saved the lamb in the wolfן¿½s own jaw,\r\nֲ ֲ ֲ ֲ And thatן¿½s my moral. The tale, I fear,\r\nֲ ֲ ֲ ֲ But poorly told. Yet it strikes me here\r\nֲ ֲ ֲ ֲ Is stuff for a moral. Whatן¿½s your view?\r\nֲ ֲ ֲ ֲ You smile, Don Pancho. Ah! thatן¿½s like you!",
  "writer": "Bret Harte (Francis)",
  "category": [
    "classic"
  ],
  "meaning": "This evocative piece by Bret Harte (Francis) represents a masterful exploration of classic. The lines capture a profound emotional resonance, inviting the reader to reflect on the deeper themes of human experience and artistic expression.\n\nIn the broader context of Bret Harte (Francis)'s bibliography, these specific lines stand out for their clarity and poignancy. Whether you are searching for inspiration or a moment of quiet contemplation, this work offers a timeless perspective that transcends its original era.\n\nAt Linespedia, we have curated this specific poem to ensure it reaches a modern audience. We recommend sharing these lines as a digital poster or using them as a thoughtful caption to connect with others who appreciate the enduring beauty of verse.",
  "meta": {
    "views": 1718,
    "dates": "August 25, 1836 ן¿½ May 6, 1902"
  }
}