{
  "id": "1b4950e8fc46",
  "slug": "odes-from-horace-to-licinius-murena1-book-the-second-ode-the-tenth-1b4950e8fc46",
  "title": "Odes From Horace. - To Licinius Murena[1]. Book The Second, Ode The Tenth.",
  "content": "     Not always, dear Licinius, is it wise\r\n     On the main Sea to ply the daring Oar;\r\n     Nor is it safe, from dread of angry Skies,\r\n     Closely to press on the insidious Shore.\r\n     To no excess discerning Spirits lean,\r\n     They feel the blessings of the golden mean;\r\n     They will not grovel in the squalid cell,\r\n     Nor seek in princely domes, with envied pomp, to dwell.\n\r\n     The pine, that lifts so high her stately boughs,\r\n     Writhes in the storms, and bends beneath their might,\r\n     Innoxious while the loudest tempest blows\r\n     O'er trees, that boast a less-aspiring height.\r\n     As the wild fury of the whirlwind pours,\r\n     With direst ruin fall the loftiest towers;\r\n     And 't is the mountain's summit that, oblique,\r\n     From the dense, lurid clouds, the baleful lightnings strike.\n\r\n     A mind well disciplin'd, when Sorrow lours,\r\n     Not sullenly excludes Hope's smiling rays;\r\n     Nor, when soft Pleasure boasts of lasting powers,\r\n     With boundless trust the Promiser surveys.\r\n     It is the same dread Jove, who thro' the sky\r\n     Hurls the loud storms, that darken as they fly;\r\n     And whose benignant hand withdraws the gloom,\r\n     And spreads rekindling light, in all its living bloom.\n\r\n     To-day the Soul perceives a weight of woe; - \r\n     A brighter Morrow shall gay thoughts inspire.\r\n     Does [2]Phoebus always bend the vengeful bow?\r\n     Wakes he not often the harmonious lyre?\r\n     Be thou, when Danger scowls in every wave,\r\n     Watchful, collected, spirited, and brave;\r\n     But in the sunny sky, the flattering gales,\r\n     Contract, with steady hand, thy too expanded sails.\n",
  "writer": "Anna Seward",
  "category": [
    "classic"
  ],
  "meaning": " About: ",
  "meta": {
    "views": 4626,
    "dates": "1742-1809"
  }
}