{
  "id": "28db0d335c18",
  "slug": "fragment-of-an-antigone-28db0d335c18",
  "title": "Fragment Of An ן¿½Antigoneן¿½",
  "content": "ֲ ֲ ֲ ֲ THE CHORUS\n\r\nֲ ֲ ֲ ֲ Well hath he done who hath seizן¿½d happiness.\r\nֲ ֲ ֲ ֲ For little do the all-containing Hours,\r\nֲ ֲ ֲ ֲ Though opulent, freely give.\r\nֲ ֲ ֲ ֲ Who, weighing that life well\r\nֲ ֲ ֲ ֲ Fortune presents unprayן¿½d,\r\nֲ ֲ ֲ ֲ Declines her ministry, and carves his own:\r\nֲ ֲ ֲ ֲ And, justice not infringן¿½d,\r\nֲ ֲ ֲ ֲ Makes his own welfare his unswervן¿½d-from law.\n\r\nֲ ֲ ֲ ֲ He does well too, who keeps that clue the mild\r\nֲ ֲ ֲ ֲ Birth-Goddess and the austere Fates first gave.\r\nֲ ֲ ֲ ֲ For from the clay when these\r\nֲ ֲ ֲ ֲ Bring him, a weeping child,\r\nֲ ֲ ֲ ֲ First to the light, and mark\r\nֲ ֲ ֲ ֲ A country for him, kinsfolk, and a home,\r\nֲ ֲ ֲ ֲ Unguided he remains,\r\nֲ ֲ ֲ ֲ Till the Fates come again, alone, with death.\n\r\nֲ ֲ ֲ ֲ In little companies,\r\nֲ ֲ ֲ ֲ And, our own place once left,\r\nֲ ֲ ֲ ֲ Ignorant where to stand, or whom to avoid,\r\nֲ ֲ ֲ ֲ By city and household groupן¿½d, we live: and many shocks\r\nֲ ֲ ֲ ֲ Our order heaven-ordainן¿½d\r\nֲ ֲ ֲ ֲ Must every day endure.\r\nֲ ֲ ֲ ֲ Voyages, exiles, hates, dissensions, wars.\r\nֲ ֲ ֲ ֲ Besides what waste He makes,\r\nֲ ֲ ֲ ֲ The all-hated, order-breaking.\r\nֲ ֲ ֲ ֲ Without friend, city, or home,\r\nֲ ֲ ֲ ֲ Death, who dissevers all.\n\r\nֲ ֲ ֲ ֲ Him then I praise, who dares\r\nֲ ֲ ֲ ֲ To self-selected good\r\nֲ ֲ ֲ ֲ Prefer obedience to the primal law,\r\nֲ ֲ ֲ ֲ Which consecrates the ties of blood: for these, indeed,\r\nֲ ֲ ֲ ֲ Are to the Gods a care:\r\nֲ ֲ ֲ ֲ That touches but himself.\r\nֲ ֲ ֲ ֲ For every day man may be linkן¿½d and loos ן¿½d\r\nֲ ֲ ֲ ֲ With strangers: but the bond\r\nֲ ֲ ֲ ֲ Original, deep-inwound,\r\nֲ ֲ ֲ ֲ Of blood, can he not bind\r\nֲ ֲ ֲ ֲ Nor, if Fate binds, not bear.\n\r\nֲ ֲ ֲ ֲ But hush! Haemon, whom Antigone,\r\nֲ ֲ ֲ ֲ Robbing herself of life in burying,\r\nֲ ֲ ֲ ֲ Against Creonן¿½s law, Polynices,\r\nֲ ֲ ֲ ֲ Robs of a lovן¿½d bride; pale, imploring,\r\nֲ ֲ ֲ ֲ Waiting her passage,\r\nֲ ֲ ֲ ֲ Forth from the palace hitherward comes.\n\r\nֲ ֲ ֲ ֲ HAEMON\n\r\nֲ ֲ ֲ ֲ No, no, old men, Creon I curse not.\r\nֲ ֲ ֲ ֲ I weep, Thebans,\r\nֲ ֲ ֲ ֲ One than Creon crueller far.\r\nֲ ֲ ֲ ֲ For he, he, at least, by slaying her,\r\nֲ ֲ ֲ ֲ August laws doth mightily vindicate:\r\nֲ ֲ ֲ ֲ But thou, too-bold, headstrong, pitiless,\r\nֲ ֲ ֲ ֲ Ah me!, honourest more than thy lover,\r\nֲ ֲ ֲ ֲ O Antigone,\r\nֲ ֲ ֲ ֲ A dead, ignorant, thankless corpse.\n\r\nֲ ֲ ֲ ֲ THE CHORUS\n\r\nֲ ֲ ֲ ֲ Nor was the love untrue\r\nֲ ֲ ֲ ֲ Which the Dawn-Goddess bore\r\nֲ ֲ ֲ ֲ To that fair youth she erst\r\nֲ ֲ ֲ ֲ Leaving the salt sea-beds\r\nֲ ֲ ֲ ֲ And coming flushן¿½d over the stormy frith\r\nֲ ֲ ֲ ֲ Of loud Euripus, saw\r\nֲ ֲ ֲ ֲ Saw and snatchן¿½d, wild with love,\r\nֲ ֲ ֲ ֲ From the pine-dotted spurs\r\nֲ ֲ ֲ ֲ Of Parnes, where thy waves,\r\nֲ ֲ ֲ ֲ Asopus, gleam rock-hemmן¿½d;\r\nֲ ֲ ֲ ֲ The Hunter of the Tanagraean Field.\r\nֲ ֲ ֲ ֲ But him, in his sweet prime,\r\nֲ ֲ ֲ ֲ By severance immature,\r\nֲ ֲ ֲ ֲ By Artemisן¿½ soft shafts,\r\nֲ ֲ ֲ ֲ She, though a Goddess born,\r\nֲ ֲ ֲ ֲ Saw in the rocky isle of Delos die.\r\nֲ ֲ ֲ ֲ Such end oן¿½ertook that love.\r\nֲ ֲ ֲ ֲ For she desirן¿½d to make\r\nֲ ֲ ֲ ֲ Immortal mortal man,\r\nֲ ֲ ֲ ֲ And blend his happy life,\r\nֲ ֲ ֲ ֲ Far from the Gods, with hers:\r\nֲ ֲ ֲ ֲ To him postponing an eternal law.\n\r\nֲ ֲ ֲ ֲ HAEMON\n\r\nֲ ֲ ֲ ֲ But, like me, she, wroth, complaining,\r\nֲ ֲ ֲ ֲ Succumbן¿½d to the envy of unkind Gods:\r\nֲ ֲ ֲ ֲ And, her beautiful arms unclasping,\r\nֲ ֲ ֲ ֲ Her fair Youth unwillingly gave.\n\r\nֲ ֲ ֲ ֲ THE CHORUS\n\r\nֲ ֲ ֲ ֲ Nor, though enthronן¿½d too high\r\nֲ ֲ ֲ ֲ To fear assault of envious Gods,\r\nֲ ֲ ֲ ֲ His belovן¿½d Argive Seer would Zeus retain\r\nֲ ֲ ֲ ֲ From his appointed end\r\nֲ ֲ ֲ ֲ In this our Thebes: but when\n\r\nֲ ֲ ֲ ֲ His flying steeds came near\r\nֲ ֲ ֲ ֲ To cross the steep Ismenian glen,\r\nֲ ֲ ֲ ֲ The broad Earth openן¿½d and whelmן¿½d them and him;\r\nֲ ֲ ֲ ֲ And through the void air sang\r\nֲ ֲ ֲ ֲ At large his enemyן¿½s spear.\n\r\nֲ ֲ ֲ ֲ And fain would Zeus have savן¿½d his tired son\r\nֲ ֲ ֲ ֲ Beholding him where the Two Pillars stand\r\nֲ ֲ ֲ ֲ Oן¿½er the sun-reddenן¿½d Western Straits:\r\nֲ ֲ ֲ ֲ Or at his work in that dim lower world.\r\nֲ ֲ ֲ ֲ Fain would he have recallן¿½d\r\nֲ ֲ ֲ ֲ The fraudulent oath which bound\r\nֲ ֲ ֲ ֲ To a much feebler wight the heroic man:\n\r\nֲ ֲ ֲ ֲ But he preferrן¿½d Fate to his strong desire.\r\nֲ ֲ ֲ ֲ Nor did there need less than the burning pile\r\nֲ ֲ ֲ ֲ Under the towering Trachis crags,\r\nֲ ֲ ֲ ֲ And the Spercheiusן¿½ vale, shaken with groans,\r\nֲ ֲ ֲ ֲ And the rousן¿½d Maliac gulph,\r\nֲ ֲ ֲ ֲ And scarן¿½d Oetaean snows,\r\nֲ ֲ ֲ ֲ To achieve his sonן¿½s deliverance, O my child.",
  "writer": "Matthew Arnold",
  "category": [
    "classic"
  ],
  "meaning": "This evocative piece by Matthew Arnold represents a masterful exploration of classic. The lines capture a profound emotional resonance, inviting the reader to reflect on the deeper themes of human experience and artistic expression.\n\nIn the broader context of Matthew Arnold's bibliography, these specific lines stand out for their clarity and poignancy. Whether you are searching for inspiration or a moment of quiet contemplation, this work offers a timeless perspective that transcends its original era.\n\nAt Linespedia, we have curated this specific poem to ensure it reaches a modern audience. We recommend sharing these lines as a digital poster or using them as a thoughtful caption to connect with others who appreciate the enduring beauty of verse.",
  "meta": {
    "views": 1899,
    "dates": "24 December 1822 - 15 April 1888"
  }
}