{
  "id": "382b03559932",
  "slug": "the-fog-382b03559932",
  "title": "The Fog",
  "content": "    Out of the lamp-bestarred and clouded dusk - \r\n    Snaring, illuding, concealing,\r\n    Magically conjuring - \r\n    Turning to fairy-coaches\r\n    Beetle-backed limousines\r\n    Scampering under the great Arch - \r\n    Making a decoy of blue overalls\r\n    And mystery of a scarlet shawl - \r\n    Indolently - \r\n    Knowing no impediment of its sure advance - \r\n    Descends the fog.",
  "writer": "Lola Ridge",
  "category": [
    "classic"
  ],
  "meaning": "This evocative piece by Lola Ridge represents a masterful exploration of classic. The lines capture a profound emotional resonance, inviting the reader to reflect on the deeper themes of human experience and artistic expression.\n\nIn the broader context of Lola Ridge's bibliography, these specific lines stand out for their clarity and poignancy. Whether you are searching for inspiration or a moment of quiet contemplation, this work offers a timeless perspective that transcends its original era.\n\nAt Linespedia, we have curated this specific poem to ensure it reaches a modern audience. We recommend sharing these lines as a digital poster or using them as a thoughtful caption to connect with others who appreciate the enduring beauty of verse.",
  "meta": {
    "views": 1590,
    "dates": "December 12, 1873 - May 19, 1941"
  }
}