{
  "id": "3ee2ee39f875",
  "slug": "a-last-word-3ee2ee39f875",
  "title": "A Last Word",
  "content": "    Oh, for some cup of consummating might,\r\n    Filled with life's kind conclusion, lost in night!\r\n    A wine of darkness, that with death shall cure\r\n    This sickness called existence! Oh to find\r\n    Surcease of sorrow! quiet for the mind,\r\n    An end of thought in something dark and sure!\r\n    Mandrake and hellebore, or poison pure!\r\n    Some drug of death, wherein there are no dreams!\r\n    No more, no more, with patience, to endure\r\n    The wrongs of life, the hate of men, it seems;\r\n    Or wealth's authority, tyranny of time,\r\n    And lamentations and the boasts of man!\r\n    To hear no more the wild complaints of toil,\r\n    And struggling merit, that, unknown, must starve:\r\n    To see no more life's disregard for Art!\r\n    Oh God! to know no longer anything!\r\n    Nor good, nor evil, or what either means!\r\n    Nor hear the changing tides of customs roll\r\n    On the dark shores of Time! No more to hear\r\n    The stream of Life that furies on the shoals\r\n    Of hard necessity! No more to see\r\n    The unavailing battle waged of Need\r\n    Against adversity! Merely to lie, at last,\r\n    Pulseless and still, at peace beneath the sod!\r\n    To think and dream no more! no more to hope!\r\n    At rest at last! at last at peace and rest,\r\n    Clasped by some kind tree's gnarled arm of root\r\n    Bearing me upward in its large embrace\r\n    To gentler things and fairer clouds and winds,\r\n    And stars and sun and moon! To undergo\r\n    The change the great trees know when Spring comes in\r\n    With shoutings and rejoicings of the rain,\r\n    To swiftly rise an atom in a host,\r\n    The myriad army of the leaves; and stand\r\n    A handsbreadth nearer Heaven and what is God!\r\n    To pulse in sap that beats unfevered in\r\n    The life we call inanimate the heart\r\n    Of some great tree. And so, unconsciously,\r\n    As sleeps a child, clasped in its mother's arm,\r\n    Be taken back, in amplitudes of grace,\r\n    To Nature's heart, and so be lost in her.",
  "writer": "Madison Julius Cawein",
  "category": [
    "classic"
  ],
  "meaning": "This evocative piece by Madison Julius Cawein represents a masterful exploration of classic. The lines capture a profound emotional resonance, inviting the reader to reflect on the deeper themes of human experience and artistic expression.\n\nIn the broader context of Madison Julius Cawein's bibliography, these specific lines stand out for their clarity and poignancy. Whether you are searching for inspiration or a moment of quiet contemplation, this work offers a timeless perspective that transcends its original era.\n\nAt Linespedia, we have curated this specific poem to ensure it reaches a modern audience. We recommend sharing these lines as a digital poster or using them as a thoughtful caption to connect with others who appreciate the enduring beauty of verse.",
  "meta": {
    "views": 1720,
    "dates": "23 March 1865 - 8 December 1914"
  }
}