{
  "id": "40d1cf9bcad1",
  "slug": "a-whale-40d1cf9bcad1",
  "title": "A Whale.",
  "content": "    THE con-sci-en-tious art-ist tries\r\n    On-ly to draw what meets his eyes.\r\n    This is the Whale; he seems to be\r\n    A spout of wa-ter in the sea.\r\n    Now, Hux-ley from one bone could make\r\n    An un-known beast; so if I take\r\n    This spout of wa-ter, and from thence\r\n    Con-struct a Whale by in-fer-ence,\r\n    A Whale, I ven-ture to as-sert,\r\n    Must be an an-i-mat-ed squirt!\r\n    Thus, chil-dren, we the truth may sift\r\n    By use of Log-ic's Price-less Gift.",
  "writer": "Oliver Herford",
  "category": [
    "classic"
  ],
  "meaning": "This evocative piece by Oliver Herford represents a masterful exploration of classic. The lines capture a profound emotional resonance, inviting the reader to reflect on the deeper themes of human experience and artistic expression.\n\nIn the broader context of Oliver Herford's bibliography, these specific lines stand out for their clarity and poignancy. Whether you are searching for inspiration or a moment of quiet contemplation, this work offers a timeless perspective that transcends its original era.\n\nAt Linespedia, we have curated this specific poem to ensure it reaches a modern audience. We recommend sharing these lines as a digital poster or using them as a thoughtful caption to connect with others who appreciate the enduring beauty of verse.",
  "meta": {
    "views": 1639,
    "dates": "1863 - 1935"
  }
}