{
  "id": "4986f4e8d04a",
  "slug": "breitmann-in-paris-4986f4e8d04a",
  "title": "Breitmann in Paris",
  "content": "ֲ ֲ ֲ ֲ ן¿½Recessit in Franciam.ן¿½\n\r\nֲ ֲ ֲ ֲ ן¿½Et affectu pectoris,\r\nֲ ֲ ֲ ֲ Et toto gestu corporis,\r\nֲ ֲ ֲ ֲ Et scholares maxime,\r\nֲ ֲ ֲ ֲ Qui festa colunt optime.ן¿½\r\nֲ ֲ ֲ ֲ - Carmina Burana, 13th century.\n\n\n\r\nֲ ֲ ֲ ֲ Der teufelן¿½s los in Bal Mabille,\r\nֲ ֲ ֲ ֲ Dereן¿½s hell-fire in de air,\r\nֲ ֲ ֲ ֲ De fiddlers canן¿½t blay noding else\r\nֲ ֲ ֲ ֲ Boot Orphן¿½e aux Enfers:\r\nֲ ֲ ֲ ֲ Vot makes de beoples howl mit shoy?\r\nֲ ֲ ֲ ֲ Da capo Bravo! bis!!\r\nֲ ֲ ֲ ֲ Itן¿½s a Deutscher aus Amerikן¿½:\r\nֲ ֲ ֲ ֲ Hans Breitmann in Paris.\n\r\nֲ ֲ ֲ ֲ Dereן¿½s silber toughts vot might hafe peen,\r\nֲ ֲ ֲ ֲ Dereן¿½s golden deeds vot must:\r\nֲ ֲ ֲ ֲ Der Hans ish come to Frankenland\r\nֲ ֲ ֲ ֲ On one eternal bust.\r\nֲ ֲ ֲ ֲ Der same old rowdy Argonaut\r\nֲ ֲ ֲ ֲ Vot hoont de same oldt vleece,\r\nֲ ֲ ֲ ֲ A hafin all de foon dere ish\r\nֲ ֲ ֲ ֲ Der Breitmann in Paris.\n\r\nֲ ֲ ֲ ֲ Mit a gal on eider shoulder\r\nֲ ֲ ֲ ֲ A holdin py his beard,\r\nֲ ֲ ֲ ֲ He tantz de Cancan, sacrament!\r\nֲ ֲ ֲ ֲ Dill all das Volk vas skeered.\r\nֲ ֲ ֲ ֲ Like a roarin hippopatamos,\r\nֲ ֲ ֲ ֲ Mit a kangarunic shoomp,\r\nֲ ֲ ֲ ֲ Dey feared heן¿½d smash de Catacombs,\r\nֲ ֲ ֲ ֲ Each dime der Breitmann bump.\n\r\nֲ ֲ ֲ ֲ De pretty liddle cocodettes\r\nֲ ֲ ֲ ֲ Lofe efery dings ish new,\r\nֲ ֲ ֲ ֲ ן¿½Dן¿½ou vient il donc ce grand Mן¿½sieu?\r\nֲ ֲ ֲ ֲ O sacrן¿½ nom de Dieu!ן¿½\r\nֲ ֲ ֲ ֲ In fain dey kicks deir veet on high,\r\nֲ ֲ ֲ ֲ And sky like vlyin geese,\r\nֲ ֲ ֲ ֲ Dey can not kick de hat afay\r\nֲ ֲ ֲ ֲ From Breitmann in Paris.\n\r\nֲ ֲ ֲ ֲ O vhere vas id der Breitmann life?\r\nֲ ֲ ֲ ֲ Oopon de Rond Point gay,\r\nֲ ֲ ֲ ֲ Vot shdreet lie shoost pehind his house?\r\nֲ ֲ ֲ ֲ La rue de Rabelais.\r\nֲ ֲ ֲ ֲ Aroundt de corner Harperן¿½s shtands\r\nֲ ֲ ֲ ֲ Vhere Yankee drinks dey mill,\r\nֲ ֲ ֲ ֲ Vhile shdraight ahet, agross de shdreet,\r\nֲ ֲ ֲ ֲ Der lies de Bal Mabille.\n\r\nֲ ֲ ֲ ֲ Idן¿½s all along de Elysן¿½es,\r\nֲ ֲ ֲ ֲ Idן¿½s oop de Boulevarce,\r\nֲ ֲ ֲ ֲ Heן¿½s sampled all de weinshops,\r\nֲ ֲ ֲ ֲ Und heן¿½s vinked at efery garce.\r\nֲ ֲ ֲ ֲ Dou schveet plack-silken Gabrielle,\r\nֲ ֲ ֲ ֲ O let me learn from dee,\r\nֲ ֲ ֲ ֲ If ן¿½tis in lofe or absinthe drunks,\r\nֲ ֲ ֲ ֲ Dat dis wild ghost may pe?\n\r\nֲ ֲ ֲ ֲ Und dou mayן¿½st kneel in Notre Dame,\r\nֲ ֲ ֲ ֲ Und veep away dy sin,\r\nֲ ֲ ֲ ֲ Vhile I go vight at Barriere balls,\r\nֲ ֲ ֲ ֲ Oontil mine poots cave in;\r\nֲ ֲ ֲ ֲ Boot if ve pray, or if ve sin\r\nֲ ֲ ֲ ֲ Vhile nodings ish refuse,\r\nֲ ֲ ֲ ֲ Tis all de same in Paris here,\r\nֲ ֲ ֲ ֲ So long ash lן¿½on sן¿½amuse.\n\r\nֲ ֲ ֲ ֲ O life, mein dear, at pest or vorst,\r\nֲ ֲ ֲ ֲ Ish boot a vancy ball,\r\nֲ ֲ ֲ ֲ Its cratest shoy a vild gallop,\r\nֲ ֲ ֲ ֲ Vhere madness goferns all.\r\nֲ ֲ ֲ ֲ Und should dey toorn ids gas-light off,\r\nֲ ֲ ֲ ֲ Und nefer leafe a shbark,\r\nֲ ֲ ֲ ֲ Sdill Iן¿½d find my vay to Heafen or\r\nֲ ֲ ֲ ֲ Dy lips, lofe, in de dark.\n\r\nֲ ֲ ֲ ֲ O crown your het mit roses, lofe!\r\nֲ ֲ ֲ ֲ O keep a liddel sprung!\r\nֲ ֲ ֲ ֲ Oonendless wisdom ish but dis:\r\nֲ ֲ ֲ ֲ To go it vhile youן¿½re yung!\r\nֲ ֲ ֲ ֲ Und Age vas nefer coom to him,\r\nֲ ֲ ֲ ֲ To him Spring plooms afresh,\r\nֲ ֲ ֲ ֲ Who finds a livinן¿½ spirit in\r\nֲ ֲ ֲ ֲ Der Teufel und der Flesh.",
  "writer": "Charles G. Leland",
  "category": [
    "classic"
  ],
  "meaning": "This evocative piece by Charles G. Leland represents a masterful exploration of classic. The lines capture a profound emotional resonance, inviting the reader to reflect on the deeper themes of human experience and artistic expression.\n\nIn the broader context of Charles G. Leland's bibliography, these specific lines stand out for their clarity and poignancy. Whether you are searching for inspiration or a moment of quiet contemplation, this work offers a timeless perspective that transcends its original era.\n\nAt Linespedia, we have curated this specific poem to ensure it reaches a modern audience. We recommend sharing these lines as a digital poster or using them as a thoughtful caption to connect with others who appreciate the enduring beauty of verse.",
  "meta": {
    "views": 1584,
    "dates": "August 15, 1824 ן¿½ March 20, 1903"
  }
}