{
  "id": "4ba41bf48948",
  "slug": "his-meditation-upon-death-4ba41bf48948",
  "title": "His Meditation Upon Death",
  "content": "Be those few hours, which I have yet to spend,\r\nBlest with the meditation of my end;\r\nThough they be few in number, I'm content;\r\nIf otherwise, I stand indifferent,\r\nNor makes it matter, Nestor's years to tell,\r\nIf man lives long, and if he live not well.\r\nA multitude of days still heaped on\r\nSeldom brings order, but confusion.\r\nMight I make choice, long life should be with-stood;\r\nNor would I care how short it were, if good;\r\nWhich to effect, let ev'ry passing bell\r\nPossess my thoughts, next comes my doleful knell;\r\nAnd when the night persuades me to my bed,\r\nI'll think I'm going to be buried;\r\nSo shall the blankets which come over me\r\nPresent those turfs, which once must cover me;\r\nAnd with as firm behaviour I will meet\r\nThe sheet I sleep in, as my winding-sheet.\r\nWhen Sleep shall bathe his body in mine eyes,\r\nI will believe, that then my body dies;\r\nAnd if I chance to wake, and rise thereon,\r\nI'll have in mind my resurrection,\r\nWhich must produce me to that Gen'ral Doom,\r\nTo which the peasant, so the prince must come,\r\nTo hear the Judge give sentence on the Throne,\r\nWithout the least hope of affection.\r\nTears, at that day, shall make but weak defense,\r\nWhen Hell and horror fright the conscience.\r\nLet me, though late, yet at the last, begin\r\nTo shun the least temptation to a sin;\r\nThough to be tempted be no sin, until\r\nMan to th'alluring object gives his will.\r\nSuch let my life assure me, when my breath\r\nGoes thieving from me, I am safe in death;\r\nWhich is the height of comfort, when I fall,\r\nI rise triumphant in my funeral.",
  "writer": "Robert Herrick",
  "category": [
    "classic"
  ],
  "meaning": "This evocative piece by Robert Herrick represents a masterful exploration of classic. The lines capture a profound emotional resonance, inviting the reader to reflect on the deeper themes of human experience and artistic expression.\n\nIn the broader context of Robert Herrick's bibliography, these specific lines stand out for their clarity and poignancy. Whether you are searching for inspiration or a moment of quiet contemplation, this work offers a timeless perspective that transcends its original era.\n\nAt Linespedia, we have curated this specific poem to ensure it reaches a modern audience. We recommend sharing these lines as a digital poster or using them as a thoughtful caption to connect with others who appreciate the enduring beauty of verse.",
  "meta": {
    "views": 1844,
    "dates": "Baptized - August 24, 1591- October 1674"
  }
}