{
  "id": "4f3bc7b3c482",
  "slug": "unity-4f3bc7b3c482",
  "title": "Unity",
  "content": "    I dreamed that life and time and space were one,\r\n        And the pure trance of dawn;\r\n        The increase drawn\r\n    From all the journeys of the travelling sun,\r\n    And the long mysteries of sound and sight,\r\n        The whispering rains,\r\n    And far, calm waters set in lonely plains,\r\n        And cry of birds at night.\n\r\n    I dreamed that these and love and death were one,\r\n        And all eternity,\r\n        The life to be\r\n    Therewith entwined, throughout the ages spun;\r\n    And so with Grief, my playmate; him I knew\r\n        One with the rest, - \r\n    One with the mounting day, the east and west - \r\n        Lord, is it true?\r\n    Lord, do I dream? Methinks a key unlocks\r\n    Some dungeon door, in thrall of blackened towers,\r\n    On ecstasies, half hid, like chill white flowers\r\n    Blown in the secret places of the rocks.",
  "writer": "Violet Jacob",
  "category": [
    "classic"
  ],
  "meaning": "This evocative piece by Violet Jacob represents a masterful exploration of classic. The lines capture a profound emotional resonance, inviting the reader to reflect on the deeper themes of human experience and artistic expression.\n\nIn the broader context of Violet Jacob's bibliography, these specific lines stand out for their clarity and poignancy. Whether you are searching for inspiration or a moment of quiet contemplation, this work offers a timeless perspective that transcends its original era.\n\nAt Linespedia, we have curated this specific poem to ensure it reaches a modern audience. We recommend sharing these lines as a digital poster or using them as a thoughtful caption to connect with others who appreciate the enduring beauty of verse.",
  "meta": {
    "views": 2463,
    "dates": "1 September 1863 - 9 September 1946"
  }
}