{
  "id": "5bd846f1ba24",
  "slug": "a-song-upon-silvia-5bd846f1ba24",
  "title": "A Song Upon Silvia.",
  "content": "    From me my Silvia ran away,\r\n    And running therewithal\r\n    A primrose bank did cross her way,\r\n    And gave my love a fall.\n\r\n    But trust me now, I dare not say\r\n    What I by chance did see;\r\n    But such the drap'ry did betray\r\n    That fully ravished me.",
  "writer": "Robert Herrick",
  "category": [
    "classic"
  ],
  "meaning": "This evocative piece by Robert Herrick represents a masterful exploration of classic. The lines capture a profound emotional resonance, inviting the reader to reflect on the deeper themes of human experience and artistic expression.\n\nIn the broader context of Robert Herrick's bibliography, these specific lines stand out for their clarity and poignancy. Whether you are searching for inspiration or a moment of quiet contemplation, this work offers a timeless perspective that transcends its original era.\n\nAt Linespedia, we have curated this specific poem to ensure it reaches a modern audience. We recommend sharing these lines as a digital poster or using them as a thoughtful caption to connect with others who appreciate the enduring beauty of verse.",
  "meta": {
    "views": 1743,
    "dates": "Baptized - August 24, 1591- October 1674"
  }
}