{
  "id": "623ebb8fbc67",
  "slug": "a-drinking-song-623ebb8fbc67",
  "title": "A Drinking Song",
  "content": "    Come, brothers, share the fellowship\r\n    We celebrate to-night;\r\n    There's grace of song on every lip\r\n    And every heart is light!\r\n    But first, before our mentor chimes\r\n    The hour of jubilee,\r\n    Let's drink a health to good old times,\r\n    And good times yet to be!\r\n    Clink, clink, clink!\r\n    Merrily let us drink!\r\n    There's store of wealth\r\n    And more of health\r\n    In every glass, we think.\r\n    Clink, clink, clink!\r\n    To fellowship we drink!\r\n    And from the bowl\r\n    No genial soul\r\n    In such an hour can shrink.\n\r\n    And you, oh, friends from west and east\r\n    And other foreign parts,\r\n    Come share the rapture of our feast,\r\n    The love of loyal hearts;\r\n    And in the wassail that suspends\r\n    All matters burthensome,\r\n    We'll drink a health to good old friends\r\n    And good friends yet to come.\r\n    Clink, clink, clink!\r\n    To fellowship we drink!\r\n    And from the bowl\r\n    No genial soul\r\n    In such an hour will shrink.\r\n    Clink, clink, clink!\r\n    Merrily let us drink!\r\n    There's fellowship\r\n    In every sip\r\n    Of friendship's brew, we think.",
  "writer": "Eugene Field",
  "category": [
    "classic"
  ],
  "meaning": "This evocative piece by Eugene Field represents a masterful exploration of classic. The lines capture a profound emotional resonance, inviting the reader to reflect on the deeper themes of human experience and artistic expression.\n\nIn the broader context of Eugene Field's bibliography, these specific lines stand out for their clarity and poignancy. Whether you are searching for inspiration or a moment of quiet contemplation, this work offers a timeless perspective that transcends its original era.\n\nAt Linespedia, we have curated this specific poem to ensure it reaches a modern audience. We recommend sharing these lines as a digital poster or using them as a thoughtful caption to connect with others who appreciate the enduring beauty of verse.",
  "meta": {
    "views": 1824,
    "dates": "September 2, 1850 - November 4, 1895"
  }
}