{
  "id": "685b99dbee0a",
  "slug": "ecce-puer-685b99dbee0a",
  "title": "Ecce Puer",
  "content": "    Of the dark past\r\n    A child is born;\r\n    With joy and grief\r\n    My heart is torn.\n\r\n    Calm in his cradle\r\n    The living lies.\r\n    May love and mercy\r\n    Unclose his eyes!\n\r\n    Young life is breathed\r\n    On the glass;\r\n    The world that was not\r\n    Comes to pass.\n\r\n    A child is sleeping:\r\n    An old man gone.\r\n    O, father forsaken,\r\n    Forgive your son!",
  "writer": "James Joyce",
  "category": [
    "classic"
  ],
  "meaning": "This evocative piece by James Joyce represents a masterful exploration of classic. The lines capture a profound emotional resonance, inviting the reader to reflect on the deeper themes of human experience and artistic expression.\n\nIn the broader context of James Joyce's bibliography, these specific lines stand out for their clarity and poignancy. Whether you are searching for inspiration or a moment of quiet contemplation, this work offers a timeless perspective that transcends its original era.\n\nAt Linespedia, we have curated this specific poem to ensure it reaches a modern audience. We recommend sharing these lines as a digital poster or using them as a thoughtful caption to connect with others who appreciate the enduring beauty of verse.",
  "meta": {
    "views": 2185,
    "dates": "2 February 1882 - 13 January 1941"
  }
}