{
  "id": "6896da525401",
  "slug": "sampan-song-6896da525401",
  "title": "Sampan Song",
  "content": "    A little breeze blew over the sea,\r\n        And it came from far away,\r\n    Across the fields of millet and rice,\r\n    All warm with sunshine and sweet with spice,\r\n    It lifted his curls and kissed him thrice,\r\n        As upon the deck he lay.\n\r\n    It said, \"Oh, idle upon the sea,\r\n        Awake and with sleep have done,\r\n    Haul up the widest sail of the prow,\r\n    And come with me to the rice fields now,\r\n    She longs, oh, how can I tell you how,\r\n        To show you your first-born son!\"",
  "writer": "Laurence Hope (Adela Florence Cory Nicolson)",
  "category": [
    "classic"
  ],
  "meaning": "This evocative piece by Laurence Hope (Adela Florence Cory Nicolson) represents a masterful exploration of classic. The lines capture a profound emotional resonance, inviting the reader to reflect on the deeper themes of human experience and artistic expression.\n\nIn the broader context of Laurence Hope (Adela Florence Cory Nicolson)'s bibliography, these specific lines stand out for their clarity and poignancy. Whether you are searching for inspiration or a moment of quiet contemplation, this work offers a timeless perspective that transcends its original era.\n\nAt Linespedia, we have curated this specific poem to ensure it reaches a modern audience. We recommend sharing these lines as a digital poster or using them as a thoughtful caption to connect with others who appreciate the enduring beauty of verse.",
  "meta": {
    "views": 2087,
    "dates": "1865 - 1904"
  }
}