{
  "id": "693259aecac2",
  "slug": "god-bless-our-native-land-693259aecac2",
  "title": "God Bless Our Native Land.",
  "content": "     God bless our native land,\r\n         Land of the newly free,\r\n     Oh may she ever stand\r\n         For truth and liberty.\n\r\n     God bless our native land,\r\n         Where sleep our kindred dead,\r\n     Let peace at thy command\r\n         Above their graves be shed.\n\r\n     God help our native land,\r\n         Bring surcease to her strife,\r\n     And shower from thy hand\r\n         A more abundant life.\n\r\n     God bless our native land,\r\n         Her homes and children bless,\r\n     Oh may she ever stand\r\n         For truth and righteousness.",
  "writer": "Frances Ellen Watkins Harper",
  "category": [
    "classic"
  ],
  "meaning": "This evocative piece by Frances Ellen Watkins Harper represents a masterful exploration of classic. The lines capture a profound emotional resonance, inviting the reader to reflect on the deeper themes of human experience and artistic expression.\n\nIn the broader context of Frances Ellen Watkins Harper's bibliography, these specific lines stand out for their clarity and poignancy. Whether you are searching for inspiration or a moment of quiet contemplation, this work offers a timeless perspective that transcends its original era.\n\nAt Linespedia, we have curated this specific poem to ensure it reaches a modern audience. We recommend sharing these lines as a digital poster or using them as a thoughtful caption to connect with others who appreciate the enduring beauty of verse.",
  "meta": {
    "views": 1674,
    "dates": "24 September 1825 - 22 February 1911"
  }
}