{
  "id": "6b37c6459093",
  "slug": "doubting-6b37c6459093",
  "title": "Doubting",
  "content": "ֲ ֲ ֲ ֲ A brother wandered forth with me,\r\nֲ ֲ ֲ ֲ Beside a barren beach:\r\nֲ ֲ ֲ ֲ He harped on things beyond the sea,\r\nֲ ֲ ֲ ֲ And out of reach.\n\r\nֲ ֲ ֲ ֲ He hinted once of unknown skies,\r\nֲ ֲ ֲ ֲ And then I would not hark,\r\nֲ ֲ ֲ ֲ But turned away from steadfast eyes,\r\nֲ ֲ ֲ ֲ Into the dark.\n\r\nֲ ֲ ֲ ֲ And said ן¿½an ancient faith is dead\r\nֲ ֲ ֲ ֲ And wonder fills my mind:\r\nֲ ֲ ֲ ֲ I marvel how the blind have led\r\nֲ ֲ ֲ ֲ So long the blind.\n\r\nֲ ֲ ֲ ֲ ן¿½Behold this truth we only know\r\nֲ ֲ ֲ ֲ That night is on the land!\r\nֲ ֲ ֲ ֲ And we a weary way must go\r\nֲ ֲ ֲ ֲ To find Godן¿½s hand.ן¿½\n\r\nֲ ֲ ֲ ֲ I wept ן¿½Our fathers told us, Lord,\r\nֲ ֲ ֲ ֲ That Thou wert kind and just,\r\nֲ ֲ ֲ ֲ But lo! our wailings fly abroad\r\nֲ ֲ ֲ ֲ For broken trust.\n\r\nֲ ֲ ֲ ֲ ן¿½How many evil ones are here\r\nֲ ֲ ֲ ֲ Who mocking go about,\r\nֲ ֲ ֲ ֲ Because we are too faint with fear\r\nֲ ֲ ֲ ֲ To wrestle Doubt!\n\r\nֲ ֲ ֲ ֲ ן¿½Thy riddles are beyond the ken\r\nֲ ֲ ֲ ֲ Of creatures of the sod:\r\nֲ ֲ ֲ ֲ Remember that we are but men,\r\nֲ ֲ ֲ ֲ And Thou art God!\n\r\nֲ ֲ ֲ ֲ ן¿½O, doting world, methinks your stay\r\nֲ ֲ ֲ ֲ Is weaker than a reed!\r\nֲ ֲ ֲ ֲ Our Father turns His face away;\r\nֲ ֲ ֲ ֲ ן¿½Tis dark indeed.ן¿½\n\r\nֲ ֲ ֲ ֲ The evening woods lay huddled there,\r\nֲ ֲ ֲ ֲ All wrapped in silence strange:\r\nֲ ֲ ֲ ֲ A sudden wind and lo! the air\r\nֲ ֲ ֲ ֲ Was filled with change.\n\r\nֲ ֲ ֲ ֲ ן¿½Your words are wild,ן¿½ my brother said,\r\nֲ ֲ ֲ ֲ ן¿½For Godן¿½s voice fills the breeze;\r\nֲ ֲ ֲ ֲ Go hide yourself, as Adam did,\r\nֲ ֲ ֲ ֲ Amongst the trees.\n\r\nֲ ֲ ֲ ֲ ן¿½I pluck the shoes from off my feet,\r\nֲ ֲ ֲ ֲ But dare to look around;\r\nֲ ֲ ֲ ֲ Behold,ן¿½ he said, ן¿½my Lord I greet,\r\nֲ ֲ ֲ ֲ On holy ground!ן¿½\n\r\nֲ ֲ ֲ ֲ And God spake through the wind to me\r\nֲ ֲ ֲ ֲ ן¿½Shake off that gloom of Fear,\r\nֲ ֲ ֲ ֲ You fainting soul who could not see\r\nֲ ֲ ֲ ֲ That I was near.\n\r\nֲ ֲ ֲ ֲ ן¿½Why vex me crying day and night?\r\nֲ ֲ ֲ ֲ You call on me to hark!\r\nֲ ֲ ֲ ֲ But when I bless your world with light,\r\nֲ ֲ ֲ ֲ Who makes it dark?\n\r\nֲ ֲ ֲ ֲ ן¿½Is there a ravelled riddle left\r\nֲ ֲ ֲ ֲ That you would have undone?\r\nֲ ֲ ֲ ֲ What other doubts are there to sift?ן¿½\r\nֲ ֲ ֲ ֲ I answered ן¿½None.ן¿½\n\r\nֲ ֲ ֲ ֲ ן¿½My son, look up, if you would see\r\nֲ ֲ ֲ ֲ The Promise on your way,\r\nֲ ֲ ֲ ֲ And turn a trustful face to me.ן¿½\r\nֲ ֲ ֲ ֲ I whispered ן¿½Yea.ן¿½",
  "writer": "Henry Kendall",
  "category": [
    "classic"
  ],
  "meaning": "This evocative piece by Henry Kendall represents a masterful exploration of classic. The lines capture a profound emotional resonance, inviting the reader to reflect on the deeper themes of human experience and artistic expression.\n\nIn the broader context of Henry Kendall's bibliography, these specific lines stand out for their clarity and poignancy. Whether you are searching for inspiration or a moment of quiet contemplation, this work offers a timeless perspective that transcends its original era.\n\nAt Linespedia, we have curated this specific poem to ensure it reaches a modern audience. We recommend sharing these lines as a digital poster or using them as a thoughtful caption to connect with others who appreciate the enduring beauty of verse.",
  "meta": {
    "views": 1944,
    "dates": "April 18, 1839 - August 1, 1882"
  }
}