{
  "id": "6d840ec1209b",
  "slug": "a-dream-of-spring-6d840ec1209b",
  "title": "A Dream Of Spring.",
  "content": "    The world is asleep!    All hushed is Nature's warm, sweet breath.\r\n    The world is asleep, and dreaming the silent dream of snow,\r\n    But through the silence that seems like the silence of death,\r\n    Under their shroud of ermine, the souls of the roses glow.\n\r\n    And forever the heart of the water throbs and beats,\r\n    Though bound by a million gleaming fetters and crystal rings,\r\n    No sound on lonesome mornings the lonely watcher greets,\r\n    But the frosty pane is impressed with the shadow of coming wings.",
  "writer": "Marietta Holley",
  "category": [
    "classic"
  ],
  "meaning": "This evocative piece by Marietta Holley represents a masterful exploration of classic. The lines capture a profound emotional resonance, inviting the reader to reflect on the deeper themes of human experience and artistic expression.\n\nIn the broader context of Marietta Holley's bibliography, these specific lines stand out for their clarity and poignancy. Whether you are searching for inspiration or a moment of quiet contemplation, this work offers a timeless perspective that transcends its original era.\n\nAt Linespedia, we have curated this specific poem to ensure it reaches a modern audience. We recommend sharing these lines as a digital poster or using them as a thoughtful caption to connect with others who appreciate the enduring beauty of verse.",
  "meta": {
    "views": 1662,
    "dates": "1836-1926"
  }
}