{
  "id": "85ed47c33eb1",
  "slug": "the-abbot-of-innisfallen-85ed47c33eb1",
  "title": "The Abbot Of Innisfallen",
  "content": "The Abbot of Innisfallen\r\nawoke ere dawn of day;\r\nUnder the dewy green leaves\r\nwent he forth to pray.\r\nThe lake around his island\r\nlay smooth and dark and deep,\r\nAnd wrapt in a misty stillness\r\nthe mountains were all asleep.\r\nLow kneel'd the Abbot Cormac\r\nwhen the dawn was dim and gray;\r\nThe prayers of his holy office\r\nhe faithfully 'gan say.\r\nLow kneel'd the Abbot Cormac\r\nwhile the dawn was waxing red;\r\nAnd for his sins' forgiveness\r\na solemn prayer he said:\r\nLow kneel'd that holy Abbot\r\nwhile the dawn was waxing clear;\r\nAnd he pray'd with loving-kindness\r\nfor his convent-brethren dear.\r\nLow kneel'd that blessed Abbot\r\nwhile the dawn was waxing bright;\r\nHe pray'd a great prayer for Ireland,\r\nhe pray'd with all his might.\r\nLow kneel'd that good old Father\r\nwhile the sun began to dart;\r\nHe pray'd a prayer for all men,\r\nhe pray'd it from his heart.\r\nHis blissful soul was in Heaven,\r\ntho' a breathing man was he;\r\nHe was out of time's dominion,\r\nso far as the living may be.\n\r\nThe Abbot of Innisfallen\r\narose upon his feet;\r\nHe heard a small bird singing,\r\nand O but it sung sweet!\r\nIt sung upon a holly-bush,\r\nthis little snow-white bird;\r\nA song so full of gladness\r\nhe never before had heard.\r\nIt sung upon a hazel,\r\nit sung upon a thorn;\r\nHe had never heard such music\r\nsince the hour that he was born.\r\nIt sung upon a sycamore,\r\nit sung upon a briar;\r\nTo follow the song and hearken\r\nthis Abbot could never tire.\r\nTill at last he well bethought him;\r\nhe might no longer stay;\r\nSo he bless'd the little white singing-bird,\r\nand gladly went his way.\n\r\nBut, when he came to his Abbey,\r\nhe found a wondrous change;\r\nHe saw no friendly faces there,\r\nfor every face was strange.\r\nThe strange men spoke unto him;\r\nand he heard from all and each\r\nThe foreign tongue of the Sassenach,\r\nnot wholesome Irish speech.\r\nThen the oldest monk came forward,\r\nin Irish tongue spake he:\r\n'Thou wearest the holy Augustine's dress,\r\nand who hath given it to thee?'\r\n'I wear the Augustine's dress,\r\nand Cormac is my name,\r\nThe Abbot of this good Abbey\r\nby grace of God I am.\r\nI went forth to pray, at the dawn of day;\r\nand when my prayers were said,\r\nI hearken'd awhile to a little bird,\r\nthat sung above my head.'\r\nThe monks to him made answer,\r\n'Two hundred years have gone o'er,\r\nSince our Abbot Cormac went through the gate,\r\nand never was heard of more.\r\nMatthias now is our Abbot,\r\nand twenty have pass'd away.\r\nThe stranger is lord of Ireland;\r\nwe live in an evil day.'\r\n'Days will come and go,' he said,\r\n'and the world will pass away,\r\nIn Heaven a day is a thousand years,\r\na thousand years are a day.'\r\n'Now give me absolution;\r\nfor my time is come,' said he.\r\nAnd they gave him absolution,\r\nas speedily as might be.\r\nThen, close outside the window,\r\nthe sweetest song they heard\r\nThat ever yet since the world began\r\nwas utter'd by any bird.\r\nThe monks look'd out and saw the bird,\r\nits feathers all white and clean;\r\nAnd there in a moment, beside it,\r\nanother white bird was seen.\r\nThose two they sang together,\r\nwaved their white wings, and fled;\r\nFlew aloft, and vanish'd;\r\nbut the good old man was dead.\r\nThey buried his blessed body\r\nwhere lake and green-sward meet;\r\nA carven cross above his head,\r\na holly-bush at his feet;\r\nWhere spreads the beautiful water\r\nto gay or cloudy skies,\r\nAnd the purple peaks of Killarney\r\nfrom ancient woods arise.",
  "writer": "William Allingham",
  "category": [
    "classic"
  ],
  "meaning": " About: William Allingham (March 19, 1824 or 1828 - November 18, 1889) was an Irish man of letters and poet.\n\r\nHe was born at Ballyshannon, Donegal, and was the son of the manager of a local bank who was of English descent. He obtained a post in the custom-house of his native town and held several similar posts in Ireland and England until 1870, when he had retired from the service, and became sub-editor of Fraser's Magazine, which he edited from 1874 to 1879, in succession to James Froude. He had published a volume of Poems in 1850, followed by Day and Night Songs, a volume containing many charming lyrics, in 1855. Allingham was on terms of close friendship with DG Rossetti, who contributed to the illustration of the Songs. His Letters to Allingham (1854-1870) were edited by Dr Birkbeck Hill in 1897. Lawrence Bloomfield in Ireland, his most ambitious, though not his most successful work, a narrative poem illustrative of Irish social questions, appeared in 1864. He also edited The Ballad Book for the Golden Treasury series in 1864.\n\r\nIn 1874 Allingham married Helen Paterson, known under her married name as a water-colour painter. He died at Hampstead in 1889, and his ashes are interred at St. Anne's in his native Ballyshannon.\n\r\nThough working on an unostentatious scale, Allingham produced much excellent lyrical and descriptive poetry, and the best of his pieces are thoroughly national in spirit and local colouring. His verse is clear, fresh, and graceful.",
  "meta": {
    "views": 2202,
    "dates": "March 19, 1824 or 1828 - November 18, 1889"
  }
}