{
  "id": "88ef9cf1c8b2",
  "slug": "his-grange-or-private-wealth-88ef9cf1c8b2",
  "title": "His Grange, Or Private Wealth",
  "content": "Though clock,\r\nTo tell how night draws hence, I've none,\r\nA cock\r\nI have to sing how day draws on:\r\nI have\r\nA maid, my Prue, by good luck sent,\r\nTo save\r\nThat little, Fates me gave or lent.\r\nA hen\r\nI keep, which, creeking day by day,\r\nTells when\r\nShe goes her long white egg to lay:\r\nA goose\r\nI have, which, with a jealous ear,\r\nLets loose\r\nHer tongue, to tell what danger's near.\r\nA lamb\r\nI keep, tame, with my morsels fed,\r\nWhose dam\r\nAn orphan left him, lately dead:\r\nA cat\r\nI keep, that plays about my house,\r\nGrown fat\r\nWith eating many a miching mouse:\r\nTo these\r\nA Trasy I do keep, whereby\r\nI please\r\nThe more my rural privacy:\r\nWhich are\r\nBut toys, to give my heart some ease:\r\nWhere care\r\nNone is, slight things do lightly please.",
  "writer": "Robert Herrick",
  "category": [
    "classic"
  ],
  "meaning": "This evocative piece by Robert Herrick represents a masterful exploration of classic. The lines capture a profound emotional resonance, inviting the reader to reflect on the deeper themes of human experience and artistic expression.\n\nIn the broader context of Robert Herrick's bibliography, these specific lines stand out for their clarity and poignancy. Whether you are searching for inspiration or a moment of quiet contemplation, this work offers a timeless perspective that transcends its original era.\n\nAt Linespedia, we have curated this specific poem to ensure it reaches a modern audience. We recommend sharing these lines as a digital poster or using them as a thoughtful caption to connect with others who appreciate the enduring beauty of verse.",
  "meta": {
    "views": 2185,
    "dates": "Baptized - August 24, 1591- October 1674"
  }
}