{
  "id": "9a761ecad245",
  "slug": "late-autumn-9a761ecad245",
  "title": "Late Autumn",
  "content": "October - and the skies are cool and gray\r\nO'er stubbles emptied of their latest sheaf,\r\nBare meadow, and the slowly falling leaf.\r\nThe dignity of woods in rich decay\r\nAccords full well with this majestic grief\r\nThat clothes our solemn purple hills to-day,\r\nWhose afternoon is hush'd, and wintry brief\r\nOnly a robin sings from any spray.\n\r\nAnd night sends up her pale cold moon, and spills\r\nWhite mist around the hollows of the hills,\r\nPhantoms of firth or lake; the peasant sees\r\nHis cot and stockyard, with the homestead trees,\r\nIslanded; but no foolish terror thrills\r\nHis perfect harvesting; he sleeps at ease.",
  "writer": "William Allingham",
  "category": [
    "classic"
  ],
  "meaning": "This evocative piece by William Allingham represents a masterful exploration of classic. The lines capture a profound emotional resonance, inviting the reader to reflect on the deeper themes of human experience and artistic expression.\n\nIn the broader context of William Allingham's bibliography, these specific lines stand out for their clarity and poignancy. Whether you are searching for inspiration or a moment of quiet contemplation, this work offers a timeless perspective that transcends its original era.\n\nAt Linespedia, we have curated this specific poem to ensure it reaches a modern audience. We recommend sharing these lines as a digital poster or using them as a thoughtful caption to connect with others who appreciate the enduring beauty of verse.",
  "meta": {
    "views": 2425,
    "dates": "March 19, 1824 or 1828 - November 18, 1889"
  }
}