{
  "id": "b17f4b2aba06",
  "slug": "sea-song-b17f4b2aba06",
  "title": "Sea-Song.",
  "content": "    A dash of spray,\r\n    A weed-browned way, - \r\n    My ship's in the bay,\r\n    In the glad blue bay, - \r\n    The wind's from the west\r\n    And the waves have a crest,\r\n    But my bird's in the nest\r\n    And my ship's in the bay!\n\r\n    At dawn to stand\r\n    Soft hand to hand,\r\n    Bare feet on the sand, - \r\n    On the hard brown sand, - \r\n    To wait, dew-crowned,\r\n    For the tarrying sound\r\n    Of a keel that will ground\r\n    On the scraping sand.\n\r\n    A glad surprise\r\n    In the wind-swept skies\r\n    Of my wee one's eyes, - \r\n    Those wondering eyes.\r\n    He will come, my sweet,\r\n    And will haste to meet\r\n    Those hurrying feet\r\n    And those sea-blue eyes.\n\r\n    I know the day\r\n    Must weary away,\r\n    And my ship's in the bay, - \r\n    In the clear, blue bay, - \r\n    Ah! there's wind in the west,\r\n    For the waves have a crest,\r\n    But my bird's in the nest\r\n    And my ship's in the bay!",
  "writer": "Sophie M. (Almon) Hensley",
  "category": [
    "classic"
  ],
  "meaning": "This evocative piece by Sophie M. (Almon) Hensley represents a masterful exploration of classic. The lines capture a profound emotional resonance, inviting the reader to reflect on the deeper themes of human experience and artistic expression.\n\nIn the broader context of Sophie M. (Almon) Hensley's bibliography, these specific lines stand out for their clarity and poignancy. Whether you are searching for inspiration or a moment of quiet contemplation, this work offers a timeless perspective that transcends its original era.\n\nAt Linespedia, we have curated this specific poem to ensure it reaches a modern audience. We recommend sharing these lines as a digital poster or using them as a thoughtful caption to connect with others who appreciate the enduring beauty of verse.",
  "meta": {
    "views": 1587,
    "dates": "1866-1913"
  }
}