{
  "id": "c044d9615a45",
  "slug": "the-broken-heart-c044d9615a45",
  "title": "The Broken Heart",
  "content": "News o' grief had overteaken\r\nDark-eyed Fanny, now vorseaken;\r\nThere she zot, wi' breast a-heaven,\r\nWhile vrom zide to zide, wi' grieven,\r\nVell her head, wi' tears a-creepen\r\nDown her cheaks, in bitter weepen.\r\nThere wer still the ribbon-bow\r\nShe tied avore her hour ov woe,\r\nAn' there wer still the hans that tied it\r\nHangen white,\r\nOr wringen tight,\r\nIn ceare that drowned all ceare bezide it.\n\r\nWhen a man, wi' heartless slighten,\r\nMid become a maiden's blighten,\r\nHe mid cearelessly vorseake her,\r\nBut must answer to her Meaker;\r\nHe mid slight, wi' selfish blindness,\r\nAll her deeds o' loven-kindness,\r\nGod wull waigh 'em wi' the slighten\r\nThat mid be her love's requiten;\r\nHe do look on each deceiver,\r\nHe do know\r\nWhat weight o' woe\r\nDo break the heart ov ev'ry griever.",
  "writer": "William Barnes",
  "category": [
    "classic"
  ],
  "meaning": " About: William Barnes (22nd February 1801 - 7th October 1886) was an English writer, poet, minister, and philologist. \r\nHe wrote over 800 poems, some in Dorset dialect and much other work including a comprehensive English grammar quoting from more than 70 different languages.",
  "meta": {
    "views": 2131,
    "dates": "22nd February 1801 - 7th October 1886"
  }
}