{
  "id": "e270dd2f3f97",
  "slug": "winter-e270dd2f3f97",
  "title": "Winter.",
  "content": "    With my breath so keen and chilling,\r\n        I have stripped the branches bare;\r\n    And my snow-flakes white are filling,\r\n        Feather-like, the frosty air.\n\r\n    Coming o'er the lofty mountains,\r\n        There I left a robe of white;\r\n    I have locked the sparkling fountains,\r\n        I have chained the river bright.\n\r\n    O'er the quiet valley winging,\r\n        There I left my traces, too;\r\n    Hark! the merry sleigh-bells ringing,\r\n        With their music call on you.\n\r\n    I have come! The school-boy shouting,\r\n        Joyfully brings out his sled;\r\n    He has seen me, nothing doubting,\r\n        As across the fields he sped.\n\r\n    I have come; but shall I find you\r\n        Better than the former year?\r\n    If you've cast your faults behind you,\r\n        I shall gladly greet you here.",
  "writer": "H. P. Nichols",
  "category": [
    "classic"
  ],
  "meaning": "This evocative piece by H. P. Nichols represents a masterful exploration of classic. The lines capture a profound emotional resonance, inviting the reader to reflect on the deeper themes of human experience and artistic expression.\n\nIn the broader context of H. P. Nichols's bibliography, these specific lines stand out for their clarity and poignancy. Whether you are searching for inspiration or a moment of quiet contemplation, this work offers a timeless perspective that transcends its original era.\n\nAt Linespedia, we have curated this specific poem to ensure it reaches a modern audience. We recommend sharing these lines as a digital poster or using them as a thoughtful caption to connect with others who appreciate the enduring beauty of verse.",
  "meta": {
    "views": 1819,
    "dates": null
  }
}