{
  "id": "e9ed6d988f96",
  "slug": "a-babys-death-e9ed6d988f96",
  "title": "A Baby's Death",
  "content": "    A little white soul went up to God,\r\n        Out of the mire of the city street;\r\n    It grew like a flower in the highway broad,\r\n        Close to the trample of heedless feet.\n\r\n    It fell like a snow-flake over night,\r\n        Into the ways by vile ones trod;\r\n    It sparkled--dissolved in the morning light,\r\n        And the little white soul went up to God.\n\r\n    Dainty, flower-soft, waxen thing,\r\n        Its clear eyes opened on this bad earth,\r\n    And the little shuddering soul took wing,\r\n        By the gate of death, from the gate of birth.\n\r\n    Not for those innocent lips and eyes,\r\n        The words and the ways of sin and strife;\r\n    The pure flower opened in paradise,\r\n        Fast by the banks of the river of life.\n\r\n    Yea, little victors, who never fought;\r\n        And crowned, though ye never ran the race,\r\n    His blood your innocent lives hath bought,\r\n        And ye stand before Him and see His face!\n\r\n    For this, oh Father! we give Thee thanks,\r\n        By the little graves, and the tear-wet sod,\r\n    They stand before Thee in shining ranks,\r\n        And the little white souls are safe with God!",
  "writer": "Kate Seymour Maclean",
  "category": [
    "classic"
  ],
  "meaning": "This evocative piece by Kate Seymour Maclean represents a masterful exploration of classic. The lines capture a profound emotional resonance, inviting the reader to reflect on the deeper themes of human experience and artistic expression.\n\nIn the broader context of Kate Seymour Maclean's bibliography, these specific lines stand out for their clarity and poignancy. Whether you are searching for inspiration or a moment of quiet contemplation, this work offers a timeless perspective that transcends its original era.\n\nAt Linespedia, we have curated this specific poem to ensure it reaches a modern audience. We recommend sharing these lines as a digital poster or using them as a thoughtful caption to connect with others who appreciate the enduring beauty of verse.",
  "meta": {
    "views": 4284,
    "dates": null
  }
}