{
  "id": "f2836c10b8ea",
  "slug": "the-fire-that-filled-my-heart-of-old-f2836c10b8ea",
  "title": "The Fire That Filled My Heart of Old",
  "content": "    The fire that filled my heart of old\r\n    Gave luster while it burned;\r\n    Now only ashes gray and cold\r\n    Are in its silence urned.\r\n    Ah! better was the furious flame,\r\n    The splendor with the smart;\r\n    I never cared for the singer's fame\r\n    But, oh! for the singer's heart\r\n    Once more--\r\n    The burning fulgent heart!\n\r\n    No love, no hate, no hope, no fear,\r\n    No anguish and no mirth;\r\n    Thus life extends from year to year,\r\n    A flat of sullen dearth.\r\n    Ah! life's blood creepeth cold and tame,\r\n    Life's thought plays no new part;\r\n    I never cared for the singer's fame,\r\n    But, oh! for the singer's heart\r\n    Once more--\r\n    The bleeding passionate heart!",
  "writer": "James Thomson -  (Bysshe Vanolis)",
  "category": [
    "classic"
  ],
  "meaning": " About: James Thomson (November 23, 1834 - June 3, 1882), published under the pseudonym Bysshe Vanolis, was a Victorian-era British poet famous primarily for the long poem The City of Dreadful Night (1874), an expression of bleak pessimism in a dehumanized, uncaring urban environment.",
  "meta": {
    "views": 1810,
    "dates": "November 23, 1834 - June 3, 1882"
  }
}